CHANGELOG.txt
LICENSE.txt
MANIFEST.in
README.txt
setup.py
sortingalgo/__init__.py
sortingalgo/heapsort.py
sortingalgo/mergesort.py
sortingalgo/quicksort.py
sortingalgo.egg-info/PKG-INFO
sortingalgo.egg-info/SOURCES.txt
sortingalgo.egg-info/dependency_links.txt
sortingalgo.egg-info/top_level.txt