Metadata-Version: 1.1
Name: sortingalgo
Version: 0.0.1
Summary: Sorts the Given array
Home-page: UNKNOWN
Author: Sabhya Mittal
Author-email: sabhyamittal26@gmail.com
License: MIT
Keywords: Sorting
Platform: UNKNOWN
Classifier: Intended Audience :: Education
Classifier: Operating System :: Microsoft :: Windows
Classifier: Programming Language :: Python 
